proton_driver/bufferedreader.cpython-313-x86_64-linux-gnu.so
proton_driver/client.py
proton_driver/log.py
proton_driver/errors.py
proton_driver/connection.py
proton_driver/blockstreamprofileinfo.py
proton_driver/opentelemetry.py
proton_driver/context.py
proton_driver/bufferedwriter.cpython-313-x86_64-linux-gnu.so
proton_driver/block.py
proton_driver/defines.py
proton_driver/varint.cpython-313-x86_64-linux-gnu.so
proton_driver/readhelpers.py
proton_driver/protocol.py
proton_driver/__init__.py
proton_driver/result.py
proton_driver/writer.py
proton_driver/progress.py
proton_driver/reader.py
proton_driver/clientinfo.py
proton_driver/queryprocessingstage.py
proton_driver/numpy/block.py
proton_driver/numpy/helpers.py
proton_driver/numpy/__init__.py
proton_driver/numpy/result.py
proton_driver/util/compat.py
proton_driver/util/helpers.py
proton_driver/util/__init__.py
proton_driver/util/escape.py
proton_driver/columns/datecolumn.py
proton_driver/columns/intcolumn.py
proton_driver/columns/nestedcolumn.py
proton_driver/columns/uuidcolumn.py
proton_driver/columns/nullablecolumn.py
proton_driver/columns/tuplecolumn.py
proton_driver/columns/nullcolumn.py
proton_driver/columns/exceptions.py
proton_driver/columns/service.py
proton_driver/columns/arraycolumn.py
proton_driver/columns/decimalcolumn.py
proton_driver/columns/util.py
proton_driver/columns/intervalcolumn.py
proton_driver/columns/mapcolumn.py
proton_driver/columns/__init__.py
proton_driver/columns/floatcolumn.py
proton_driver/columns/ipcolumn.py
proton_driver/columns/jsoncolumn.py
proton_driver/columns/simpleaggregatefunctioncolumn.py
proton_driver/columns/boolcolumn.py
proton_driver/columns/datetimecolumn.py
proton_driver/columns/nothingcolumn.py
proton_driver/columns/lowcardinalitycolumn.py
proton_driver/columns/stringcolumn.py
proton_driver/columns/enumcolumn.py
proton_driver/columns/base.py
proton_driver/columns/largeint.cpython-313-x86_64-linux-gnu.so
proton_driver-0.2.13.dist-info/RECORD
proton_driver-0.2.13.dist-info/METADATA
proton_driver-0.2.13.dist-info/WHEEL
proton_driver-0.2.13.dist-info/top_level.txt
proton_driver-0.2.13.dist-info/LICENSE
